sphinx_dark_scylladb_theme/404.html
sphinx_dark_scylladb_theme/__init__.py
sphinx_dark_scylladb_theme/_version.py
sphinx_dark_scylladb_theme/breadcrumbs.html
sphinx_dark_scylladb_theme/content-navigation.html
sphinx_dark_scylladb_theme/contribute.html
sphinx_dark_scylladb_theme/extensions/__init__.py
sphinx_dark_scylladb_theme/extensions/hero_box.py
sphinx_dark_scylladb_theme/extensions/labels.py
sphinx_dark_scylladb_theme/extensions/multiversion.py
sphinx_dark_scylladb_theme/extensions/navigation.py
sphinx_dark_scylladb_theme/extensions/panel_box.py
sphinx_dark_scylladb_theme/extensions/topic_box.py
sphinx_dark_scylladb_theme/extensions/utils.py
sphinx_dark_scylladb_theme/extensions/validations.py
sphinx_dark_scylladb_theme/feedback.html
sphinx_dark_scylladb_theme/footer.html
sphinx_dark_scylladb_theme/header.html
sphinx_dark_scylladb_theme/index.html
sphinx_dark_scylladb_theme/last-updated.html
sphinx_dark_scylladb_theme/layout.html
sphinx_dark_scylladb_theme/lexers/__init__.py
sphinx_dark_scylladb_theme/lexers/cql.py
sphinx_dark_scylladb_theme/lexers/ditaa.py
sphinx_dark_scylladb_theme/local-scripts.html
sphinx_dark_scylladb_theme/notice.html
sphinx_dark_scylladb_theme/promo-banner.html
sphinx_dark_scylladb_theme/scylladb-scripts.html
sphinx_dark_scylladb_theme/secondary-side-nav.html
sphinx_dark_scylladb_theme/side-nav-toggle.html
sphinx_dark_scylladb_theme/side-nav.html
sphinx_dark_scylladb_theme/static/css/main.css
sphinx_dark_scylladb_theme/static/img/.gitkeep
sphinx_dark_scylladb_theme/static/img/banner-background.svg
sphinx_dark_scylladb_theme/static/img/favicon-228x228.png
sphinx_dark_scylladb_theme/static/img/favicon-32x32.png
sphinx_dark_scylladb_theme/static/img/favicon.ico
sphinx_dark_scylladb_theme/static/img/icons/icon-about-team.svg
sphinx_dark_scylladb_theme/static/img/icons/icon-about-us-m.svg
sphinx_dark_scylladb_theme/static/img/icons/icon-about-us.svg
sphinx_dark_scylladb_theme/static/img/icons/icon-alternator.svg
sphinx_dark_scylladb_theme-0.0.3.dist-info/LICENSE
sphinx_dark_scylladb_theme-0.0.3.dist-info/METADATA
sphinx_dark_scylladb_theme-0.0.3.dist-info/WHEEL
sphinx_dark_scylladb_theme-0.0.3.dist-info/RECORD
