Metadata-Version: 2.1
Name: sphinx-dark-scylladb-theme
Version: 0.0.3
Summary: A Sphinx Theme for ScyllaDB documentation projects
Author: David García
Author-email: hi@davidgarcia.dev
Requires-Python: >=3.9,<4.0
Classifier: Programming Language :: Python :: 3
Classifier: Programming Language :: Python :: 3.9
Classifier: Programming Language :: Python :: 3.10
Classifier: Programming Language :: Python :: 3.11
Classifier: Programming Language :: Python :: 3.12
Requires-Dist: Sphinx-Substitution-Extensions (>=2022.2.16,<2023.0.0)
Requires-Dist: beautifulsoup4 (>=4.12.3,<5.0.0)
Requires-Dist: livereload (>=2.7.0,<3.0.0)
Requires-Dist: pyyaml (>=6.0.1,<7.0.0)
Requires-Dist: setuptools (>=70.1.1,<71.0.0)
Requires-Dist: sphinx-collapse (>=0.1.1,<0.2.0)
Requires-Dist: sphinx-copybutton (>=0.5.2,<0.6.0)
Requires-Dist: sphinx-notfound-page (>=1.0.2,<2.0.0)
Requires-Dist: sphinx-tabs (>=3.4.5,<4.0.0)
